scatfit-0.2.21.dist-info/entry_points.txt
scatfit-0.2.21.dist-info/LICENSE
scatfit-0.2.21.dist-info/RECORD
scatfit-0.2.21.dist-info/top_level.txt
scatfit-0.2.21.dist-info/METADATA
scatfit-0.2.21.dist-info/dependency_links.txt
scatfit-0.2.21.dist-info/WHEEL
scatfit/pulsemodels.py
scatfit/dm.py
scatfit/plotting.py
scatfit/sigproc.py
scatfit/pulsemodels_python.py
scatfit/version.py
scatfit/__init__.py
scatfit/pulsemodels_cython.cpython-311-x86_64-linux-gnu.so
scatfit/apps/fit_frb.py
scatfit/apps/simulate_pulse.py
scatfit/apps/__init__.py
