Metadata-Version: 2.1
Name: scatfit
Version: 0.2.21
Summary: Scattering fits of time domain radio signals (Fast Radio Bursts or pulsars).
Home-page: https://github.com/fjankowsk/scatfit
Author: Fabian Jankowski
Author-email: fjankowsk@gmail.com
License: MIT
Classifier: Development Status :: 5 - Production/Stable
Classifier: License :: OSI Approved :: MIT License
Classifier: Programming Language :: Python :: 2
Classifier: Programming Language :: Python :: 3
Classifier: Operating System :: OS Independent
License-File: LICENSE
Requires-Dist: astropy
Requires-Dist: corner
Requires-Dist: emcee
Requires-Dist: lmfit
Requires-Dist: matplotlib
Requires-Dist: mtcutils
Requires-Dist: numpy
Requires-Dist: pandas
Requires-Dist: scipy
Requires-Dist: tqdm
Requires-Dist: your
Provides-Extra: develop
Requires-Dist: black ; extra == 'develop'
Requires-Dist: cibuildwheel ; extra == 'develop'
Requires-Dist: Cython >=3.0.0 ; extra == 'develop'
Requires-Dist: pytest ; extra == 'develop'
Requires-Dist: pytest-cov ; extra == 'develop'
Requires-Dist: twine ; extra == 'develop'
Provides-Extra: docs
Requires-Dist: myst-parser ; extra == 'docs'
Requires-Dist: sphinx ; extra == 'docs'
Requires-Dist: sphinx-rtd-theme ; extra == 'docs'
